snowdrop_special_adjudicators/__init__.py
snowdrop_special_adjudicators/adjudicators/__init__.py
snowdrop_special_adjudicators/adjudicators/lookup_table.py
snowdrop_special_adjudicators/adjudicators/quantum_annealing.py
snowdrop_special_adjudicators/data/automorphisms_graph_number_11_max_500000.pkl
snowdrop_special_adjudicators/data/automorphisms_graph_number_12_max_500000.pkl
snowdrop_special_adjudicators/data/automorphisms_graph_number_18_max_500000.pkl
snowdrop_special_adjudicators/data/automorphisms_graph_number_19_max_500000.pkl
snowdrop_special_adjudicators/data/automorphisms_graph_number_20_max_500000.pkl
snowdrop_special_adjudicators/data/automorphisms_graph_number_24_max_500000.pkl
snowdrop_special_adjudicators/data/automorphisms_graph_number_2_max_500000.pkl
snowdrop_special_adjudicators/data/embeddings_graph_number_11_raster_breadth_2_grid_size_12_qc_Advantage2_system1.6.pkl
snowdrop_special_adjudicators/data/embeddings_graph_number_12_raster_breadth_2_grid_size_12_qc_Advantage2_system1.6.pkl
snowdrop_special_adjudicators/data/embeddings_graph_number_18_raster_breadth_2_grid_size_12_qc_Advantage2_system1.6.pkl
snowdrop_special_adjudicators/data/embeddings_graph_number_19_raster_breadth_2_grid_size_12_qc_Advantage2_system1.6.pkl
snowdrop_special_adjudicators/data/embeddings_graph_number_20_raster_breadth_2_grid_size_12_qc_Advantage2_system1.6.pkl
snowdrop_special_adjudicators/data/embeddings_graph_number_24_raster_breadth_2_grid_size_12_qc_Advantage2_system1.6.pkl
snowdrop_special_adjudicators/data/embeddings_graph_number_2_raster_breadth_2_grid_size_12_qc_Advantage2_system1.6.pkl
snowdrop_special_adjudicators/data/extract_and_compress_lookup_table_data.py
snowdrop_special_adjudicators/data/graph_11_adjudicated.pkl.gz
snowdrop_special_adjudicators/data/graph_12_adjudicated.pkl.gz
snowdrop_special_adjudicators/data/graph_18_adjudicated.pkl.gz
snowdrop_special_adjudicators/data/graph_19_adjudicated.pkl.gz
snowdrop_special_adjudicators-0.0.3.dist-info/LICENSE
snowdrop_special_adjudicators-0.0.3.dist-info/METADATA
snowdrop_special_adjudicators-0.0.3.dist-info/WHEEL
snowdrop_special_adjudicators-0.0.3.dist-info/RECORD
