Metadata-Version: 2.3
Name: snowdrop-special-adjudicators
Version: 0.0.3
Summary: Geordie's special adjudicators for the Tangled game
License: MIT
Author: Geordie Rose
Author-email: greatblueheron@users.noreply.github.com
Requires-Python: >=3.11,<3.14
Classifier: License :: OSI Approved :: MIT License
Classifier: Programming Language :: Python :: 3
Classifier: Programming Language :: Python :: 3.11
Classifier: Programming Language :: Python :: 3.12
Classifier: Programming Language :: Python :: 3.13
Requires-Dist: dwave-neal (>=0.6.0)
Requires-Dist: dwave-ocean-sdk (>=8.4.0)
Requires-Dist: snowdrop-adjudicators (>=0.0.8)
Requires-Dist: snowdrop-tangled-game-engine (>=1.0.7)
Project-URL: Bug Tracker, https://github.com/snowdropquantum/snowdrop-special-adjudicators/issues
Project-URL: Documentation, https://github.com/snowdropquantum/snowdrop-special-adjudicators
Project-URL: Homepage, https://github.com/snowdropquantum/snowdrop-special-adjudicators
Project-URL: Repository, https://github.com/snowdropquantum/snowdrop-special-adjudicators
